{
  "openapi": "3.0.4",
  "info": {
    "title": "Employee API",
    "description": "API for Employee Management",
    "version": "v1"
  },
  "paths": {
    "/api/Employee/by-id/{id}": {
      "get": {
        "tags": [
          "Employee"
        ],
        "parameters": [
          {
            "name": "id",
            "in": "path",
            "required": true,
            "schema": {
              "type": "integer",
              "format": "int32"
            }
          }
        ],
        "responses": {
          "200": {
            "description": "OK"
          }
        }
      }
    },
    "/api/Employee": {
      "get": {
        "tags": [
          "Employee"
        ],
        "responses": {
          "200": {
            "description": "OK"
          }
        }
      }
    },
    "/api/Employee/create": {
      "post": {
        "tags": [
          "Employee"
        ],
        "requestBody": {
          "content": {
            "application/json": {
              "schema": {
                "$ref": "#/components/schemas/CreateOrUpdateVM"
              }
            },
            "text/json": {
              "schema": {
                "$ref": "#/components/schemas/CreateOrUpdateVM"
              }
            },
            "application/*+json": {
              "schema": {
                "$ref": "#/components/schemas/CreateOrUpdateVM"
              }
            }
          }
        },
        "responses": {
          "200": {
            "description": "OK"
          }
        }
      }
    },
    "/api/Employee/update": {
      "put": {
        "tags": [
          "Employee"
        ],
        "requestBody": {
          "content": {
            "application/json": {
              "schema": {
                "$ref": "#/components/schemas/CreateOrUpdateVM"
              }
            },
            "text/json": {
              "schema": {
                "$ref": "#/components/schemas/CreateOrUpdateVM"
              }
            },
            "application/*+json": {
              "schema": {
                "$ref": "#/components/schemas/CreateOrUpdateVM"
              }
            }
          }
        },
        "responses": {
          "200": {
            "description": "OK"
          }
        }
      }
    },
    "/api/Employee/delete/{id}": {
      "delete": {
        "tags": [
          "Employee"
        ],
        "parameters": [
          {
            "name": "id",
            "in": "path",
            "required": true,
            "schema": {
              "type": "integer",
              "format": "int32"
            }
          }
        ],
        "responses": {
          "200": {
            "description": "OK"
          }
        }
      }
    },
    "/api/Employee/by-name/{name}": {
      "get": {
        "tags": [
          "Employee"
        ],
        "parameters": [
          {
            "name": "name",
            "in": "path",
            "required": true,
            "schema": {
              "type": "string"
            }
          }
        ],
        "responses": {
          "200": {
            "description": "OK"
          }
        }
      }
    },
    "/WeatherForecast": {
      "get": {
        "tags": [
          "WeatherForecast"
        ],
        "operationId": "GetWeatherForecast",
        "responses": {
          "200": {
            "description": "OK",
            "content": {
              "text/plain": {
                "schema": {
                  "type": "array",
                  "items": {
                    "$ref": "#/components/schemas/WeatherForecast"
                  }
                }
              },
              "application/json": {
                "schema": {
                  "type": "array",
                  "items": {
                    "$ref": "#/components/schemas/WeatherForecast"
                  }
                }
              },
              "text/json": {
                "schema": {
                  "type": "array",
                  "items": {
                    "$ref": "#/components/schemas/WeatherForecast"
                  }
                }
              }
            }
          }
        }
      }
    }
  },
  "components": {
    "schemas": {
      "CreateOrUpdateVM": {
        "type": "object",
        "properties": {
          "id": {
            "type": "integer",
            "format": "int32"
          },
          "firstName": {
            "maxLength": 20,
            "minLength": 2,
            "type": "string",
            "nullable": true
          },
          "lastName": {
            "maxLength": 20,
            "minLength": 2,
            "type": "string",
            "nullable": true
          },
          "email": {
            "type": "string",
            "format": "email",
            "nullable": true
          },
          "position": {
            "minLength": 2,
            "type": "string",
            "nullable": true
          }
        },
        "additionalProperties": false
      },
      "WeatherForecast": {
        "type": "object",
        "properties": {
          "date": {
            "type": "string",
            "format": "date"
          },
          "temperatureC": {
            "type": "integer",
            "format": "int32"
          },
          "temperatureF": {
            "type": "integer",
            "format": "int32",
            "readOnly": true
          },
          "summary": {
            "type": "string",
            "nullable": true
          }
        },
        "additionalProperties": false
      }
    }
  }
}